app/__init__.py
app/api.py
ebs/__init__.py
ebs/ebs2cx.py
ebs/test_ebs.py
gpml/__init__.py
gpml/gpml2cx.py
gsea/__init__.py
gsea/cx2gsea.py
map_enrichment/__init__.py
map_enrichment/enrich_map.py
map_enrichment/enrichment_utils.py
ndex_utils_dev-3.0.11.8.dist-info/DESCRIPTION.rst
ndex_utils_dev-3.0.11.8.dist-info/METADATA
ndex_utils_dev-3.0.11.8.dist-info/RECORD
ndex_utils_dev-3.0.11.8.dist-info/WHEEL
ndex_utils_dev-3.0.11.8.dist-info/metadata.json
ndex_utils_dev-3.0.11.8.dist-info/top_level.txt
pc/__init__.py
pc/pathway_commons_api.py
sif/__init__.py
sif/cx2sif.py
sif/sif2cx.py
tsv/__init__.py
tsv/cx2ndex.py
tsv/delim2cx.py
