Metadata-Version: 2.0
Name: ndex-utils-dev
Version: 3.0.11.8
Summary: NDEx Python utilities.  Includes file conversion and importing functions
Home-page: https://www.ndexbio.org
Author: The NDEx Project
Author-email: contact@ndexbio.org
License: BSD
Keywords: network analysis biology
Platform: UNKNOWN
Classifier: Development Status :: 4 - Beta
Classifier: Intended Audience :: Science/Research
Classifier: Topic :: Scientific/Engineering :: Information Analysis
Classifier: Topic :: Scientific/Engineering :: Bio-Informatics
Classifier: Topic :: Scientific/Engineering :: Medical Science Apps.
Classifier: License :: OSI Approved :: BSD License
Classifier: Programming Language :: Python :: 2.7
Requires-Dist: bottle
Requires-Dist: gevent
Requires-Dist: gevent-websocket
Requires-Dist: ndex
Requires-Dist: networkx
Requires-Dist: requests
Requires-Dist: requests-toolbelt
Requires-Dist: scipy
Requires-Dist: urllib3 (>=1.16)
